elfs.py
elfs-1.3.6.dist-info/LICENSE
elfs-1.3.6.dist-info/METADATA
elfs-1.3.6.dist-info/WHEEL
elfs-1.3.6.dist-info/entry_points.txt
elfs-1.3.6.dist-info/top_level.txt
elfs-1.3.6.dist-info/RECORD
