Metadata-Version: 2.1
Name: elfs
Version: 1.3.6
Summary: Almost, but not quite, entirely unlike aliases
Home-page: https://github.com/elesiuta/elfs
License: UNKNOWN
Platform: UNKNOWN
Classifier: Programming Language :: Python :: 3
Classifier: License :: OSI Approved :: MIT License
Classifier: Operating System :: OS Independent
Classifier: Environment :: Console
